LICENSE
MANIFEST.in
README.md
pyproject.toml
setup.py
wagtail_custom_code_editor/.DS_Store
wagtail_custom_code_editor/__init__.py
wagtail_custom_code_editor/apps.py
wagtail_custom_code_editor/blocks.py
wagtail_custom_code_editor/fields.py
wagtail_custom_code_editor/files.py
wagtail_custom_code_editor/panels.py
wagtail_custom_code_editor/settings.py
wagtail_custom_code_editor/validators.py
wagtail_custom_code_editor/wagtail_hooks.py
wagtail_custom_code_editor/widgets.py
wagtail_custom_code_editor.egg-info/PKG-INFO
wagtail_custom_code_editor.egg-info/SOURCES.txt
wagtail_custom_code_editor.egg-info/dependency_links.txt
wagtail_custom_code_editor.egg-info/requires.txt
wagtail_custom_code_editor.egg-info/top_level.txt
wagtail_custom_code_editor/migrations/__init__.py
wagtail_custom_code_editor/static/wagtail_custom_code_editor/ace/ace.js
wagtail_custom_code_editor/static/wagtail_custom_code_editor/ace/ext-beautify.js
wagtail_custom_code_editor/static/wagtail_custom_code_editor/ace/ext-code_lens.js
wagtail_custom_code_editor/static/wagtail_custom_code_editor/ace/ext-command_bar.js
wagtail_custom_code_editor/static/wagtail_custom_code_editor/ace/ext-elastic_tabstops_lite.js
wagtail_custom_code_editor/static/wagtail_custom_code_editor/ace/ext-emmet.js
wagtail_custom_code_editor/static/wagtail_custom_code_editor/ace/ext-error_marker.js
wagtail_custom_code_editor/static/wagtail_custom_code_editor/ace/ext-hardwrap.js
wagtail_custom_code_editor/static/wagtail_custom_code_editor/ace/ext-inline_autocomplete.js
wagtail_custom_code_editor/static/wagtail_custom_code_editor/ace/ext-keybinding_menu.js
wagtail_custom_code_editor/static/wagtail_custom_code_editor/ace/ext-language_tools.js
wagtail_custom_code_editor/static/wagtail_custom_code_editor/ace/ext-linking.js
wagtail_custom_code_editor/static/wagtail_custom_code_editor/ace/ext-modelist.js
wagtail_custom_code_editor/static/wagtail_custom_code_editor/ace/ext-options.js
wagtail_custom_code_editor/static/wagtail_custom_code_editor/ace/ext-prompt.js
wagtail_custom_code_editor/static/wagtail_custom_code_editor/ace/ext-rtl.js
wagtail_custom_code_editor/static/wagtail_custom_code_editor/ace/ext-searchbox.js
